hide_admin/__init__.py
hide_admin/admin_site.py
hide_admin/apps.py
django_hide_admin-1.0.0.dist-info/LICENSE
django_hide_admin-1.0.0.dist-info/WHEEL
django_hide_admin-1.0.0.dist-info/METADATA
django_hide_admin-1.0.0.dist-info/RECORD
